{
  "fillColor": [
    255,
    0,
    0,
    128
  ],
  "flags": {},
  "imageData": null,
  "imageHeight": 4000,
  "imagePath": "1666105525350.jpg",
  "imageWidth": 3000,
  "lineColor": [
    0,
    255,
    0,
    128
  ],
  "shapes": [
    {
      "fill_color": null,
      "flags": {},
      "id": 0,
      "label": "placa",
      "line_color": [
        210,
        185,
        26,
        255
      ],
      "points": [
        [
          1973.2471324296139,
          354.30031282586015
        ],
        [
          1979.4239631336404,
          422.51152073732715
        ]
      ],
      "shape_type": "circle"
    },
    {
      "fill_color": null,
      "flags": {},
      "id": 1,
      "label": "placa",
      "line_color": [
        87,
        122,
        177,
        255
      ],
      "points": [
        [
          1898.3009111056394,
          469.544159595368
        ],
        [
          1902.4598540145985,
          536.766423357664
        ]
      ],
      "shape_type": "circle"
    },
    {
      "fill_color": null,
      "flags": {},
      "id": 2,
      "label": "placa",
      "line_color": [
        90,
        0,
        36,
        255
      ],
      "points": [
        [
          1886.2632161026318,
          613.4087591240875
        ],
        [
          1891.6666666666665,
          683.3333333333333
        ]
      ],
      "shape_type": "circle"
    },
    {
      "fill_color": null,
      "flags": {},
      "id": 3,
      "label": "placa",
      "line_color": [
        71,
        245,
        247,
        255
      ],
      "points": [
        [
          1894.6969696969686,
          902.2727272727273
        ],
        [
          1895.9019607843134,
          973.9411764705881
        ]
      ],
      "shape_type": "circle"
    },
    {
      "fill_color": null,
      "flags": {},
      "id": 3,
      "label": "placa",
      "line_color": [
        71,
        245,
        247,
        255
      ],
      "points": [
        [
          1896.484848484848,
          1046.4848484848487
        ],
        [
          1891.1818181818176,
          1117.69696969697
        ]
      ],
      "shape_type": "circle"
    },
    {
      "fill_color": null,
      "flags": {},
      "id": 3,
      "label": "placa",
      "line_color": [
        71,
        245,
        247,
        255
      ],
      "points": [
        [
          1893.939393939394,
          756.8181818181818
        ],
        [
          1889.9393939393935,
          826.3030303030303
        ]
      ],
      "shape_type": "circle"
    },
    {
      "fill_color": null,
      "flags": {},
      "id": 4,
      "label": "placa",
      "line_color": [
        248,
        149,
        148,
        255
      ],
      "points": [
        [
          1895.1176470588234,
          1189.2352941176468
        ],
        [
          1899.4313725490192,
          1257.4705882352937
        ]
      ],
      "shape_type": "circle"
    },
    {
      "fill_color": null,
      "flags": {},
      "id": 5,
      "label": "placa",
      "line_color": [
        205,
        192,
        255,
        255
      ],
      "points": [
        [
          1894.333333333333,
          1330.0196078431372
        ],
        [
          1897.8627450980389,
          1397.4705882352937
        ]
      ],
      "shape_type": "circle"
    },
    {
      "fill_color": null,
      "flags": {},
      "id": 6,
      "label": "placa",
      "line_color": [
        240,
        15,
        153,
        255
      ],
      "points": [
        [
          1881.3921568627447,
          1467.2745098039213
        ],
        [
          1885.705882352941,
          1531.9803921568623
        ]
      ],
      "shape_type": "circle"
    },
    {
      "fill_color": null,
      "flags": {},
      "id": 7,
      "label": "placa",
      "line_color": [
        29,
        86,
        92,
        255
      ],
      "points": [
        [
          1892.7647058823527,
          1606.490196078431
        ],
        [
          1888.0588235294113,
          1674.7254901960782
        ]
      ],
      "shape_type": "circle"
    },
    {
      "fill_color": null,
      "flags": {},
      "id": 8,
      "label": "placa",
      "line_color": [
        134,
        108,
        66,
        255
      ],
      "points": [
        [
          1868.0588235294113,
          1746.490196078431
        ],
        [
          1873.156862745098,
          1816.2941176470586
        ]
      ],
      "shape_type": "circle"
    },
    {
      "fill_color": null,
      "flags": {},
      "id": 9,
      "label": "placa",
      "line_color": [
        205,
        156,
        4,
        255
      ],
      "points": [
        [
          1853.9411764705878,
          1884.5294117647054
        ],
        [
          1857.078431372549,
          1951.588235294117
        ]
      ],
      "shape_type": "circle"
    },
    {
      "fill_color": null,
      "flags": {},
      "id": 10,
      "label": "placa",
      "line_color": [
        61,
        88,
        189,
        255
      ],
      "points": [
        [
          1868.4509803921565,
          2019.8235294117644
        ],
        [
          1871.9803921568623,
          2085.313725490196
        ]
      ],
      "shape_type": "circle"
    },
    {
      "fill_color": null,
      "flags": {},
      "id": 11,
      "label": "placa",
      "line_color": [
        40,
        35,
        94,
        255
      ],
      "points": [
        [
          1877.0784313725485,
          2151.1960784313724
        ],
        [
          1875.5098039215682,
          2215.117647058823
        ]
      ],
      "shape_type": "circle"
    },
    {
      "fill_color": null,
      "flags": {},
      "id": 12,
      "label": "placa",
      "line_color": [
        168,
        12,
        125,
        255
      ],
      "points": [
        [
          1870.367240345919,
          2285.714444729856
        ],
        [
          1870.7593972086643,
          2347.6752290435816
        ]
      ],
      "shape_type": "circle"
    },
    {
      "fill_color": null,
      "flags": {},
      "id": 13,
      "label": "placa",
      "line_color": [
        79,
        106,
        8,
        255
      ],
      "points": [
        [
          1865.457831325301,
          2409.433734939759
        ],
        [
          1866.6626506024095,
          2469.072289156626
        ]
      ],
      "shape_type": "circle"
    },
    {
      "fill_color": null,
      "flags": {},
      "id": 14,
      "label": "placa",
      "line_color": [
        232,
        14,
        42,
        255
      ],
      "points": [
        [
          1850.9999999999995,
          2533.5301204819275
        ],
        [
          1849.192771084337,
          2593.7710843373493
        ]
      ],
      "shape_type": "circle"
    },
    {
      "fill_color": null,
      "flags": {},
      "id": 15,
      "label": "placa",
      "line_color": [
        155,
        123,
        39,
        255
      ],
      "points": [
        [
          1876.9036144578313,
          2667.2650602409635
        ],
        [
          1876.3012048192768,
          2730.5180722891564
        ]
      ],
      "shape_type": "circle"
    },
    {
      "fill_color": null,
      "flags": {},
      "id": 16,
      "label": "placa",
      "line_color": [
        214,
        254,
        195,
        255
      ],
      "points": [
        [
          1856.4216867469877,
          2791.9638554216863
        ],
        [
          1856.4216867469877,
          2852.807228915662
        ]
      ],
      "shape_type": "circle"
    },
    {
      "fill_color": null,
      "flags": {},
      "id": 17,
      "label": "placa",
      "line_color": [
        133,
        148,
        153,
        255
      ],
      "points": [
        [
          1841.3614457831322,
          2916.060240963855
        ],
        [
          1844.9759036144574,
          2975.6987951807228
        ]
      ],
      "shape_type": "circle"
    },
    {
      "fill_color": null,
      "flags": {},
      "id": 18,
      "label": "placa",
      "line_color": [
        131,
        255,
        215,
        255
      ],
      "points": [
        [
          1858.8313253012047,
          3035.33734939759
        ],
        [
          1864.855421686747,
          3091.3614457831322
        ]
      ],
      "shape_type": "circle"
    },
    {
      "fill_color": null,
      "flags": {},
      "id": 19,
      "label": "placa",
      "line_color": [
        82,
        10,
        195,
        255
      ],
      "points": [
        [
          1856.4216867469877,
          3157.024096385542
        ],
        [
          1854.6144578313251,
          3215.4578313253005
        ]
      ],
      "shape_type": "circle"
    },
    {
      "fill_color": null,
      "flags": {},
      "id": 20,
      "label": "placa",
      "line_color": [
        119,
        226,
        144,
        255
      ],
      "points": [
        [
          1832.9277108433735,
          3286.5421686746986
        ],
        [
          1838.9518072289156,
          3344.3734939759033
        ]
      ],
      "shape_type": "circle"
    },
    {
      "fill_color": null,
      "flags": {},
      "id": 21,
      "label": "placa",
      "line_color": [
        132,
        159,
        179,
        255
      ],
      "points": [
        [
          1917.867469879518,
          3393.771084337349
        ],
        [
          1919.6746987951806,
          3453.409638554216
        ]
      ],
      "shape_type": "circle"
    },
    {
      "fill_color": null,
      "flags": {},
      "id": 22,
      "label": "placa",
      "line_color": [
        107,
        172,
        8,
        255
      ],
      "points": [
        [
          1933.5301204819275,
          3519.67469879518
        ],
        [
          1934.1325301204815,
          3570.879518072289
        ]
      ],
      "shape_type": "circle"
    },
    {
      "fill_color": null,
      "flags": {},
      "id": 23,
      "label": "placa",
      "line_color": [
        162,
        108,
        45,
        255
      ],
      "points": [
        [
          1837.1445783132526,
          3640.759036144578
        ],
        [
          1838.9518072289156,
          3694.3734939759033
        ]
      ],
      "shape_type": "circle"
    }
  ],
  "version": "3.17.2"
}