{
  "fillColor": [
    255,
    0,
    0,
    128
  ],
  "flags": {},
  "imageData": null,
  "imageHeight": 4000,
  "imagePath": "1666086842694.jpg",
  "imageWidth": 3000,
  "lineColor": [
    0,
    255,
    0,
    128
  ],
  "shapes": [
    {
      "fill_color": null,
      "flags": {},
      "id": 0,
      "label": "placa",
      "line_color": [
        149,
        250,
        17,
        255
      ],
      "points": [
        [
          1362.963190184049,
          2105.294478527607
        ],
        [
          1364.8036809815949,
          2129.834355828221
        ]
      ],
      "shape_type": "circle"
    },
    {
      "fill_color": null,
      "flags": {},
      "id": 1,
      "label": "placa",
      "line_color": [
        129,
        171,
        79,
        255
      ],
      "points": [
        [
          1350.0797546012268,
          2167.8711656441715
        ],
        [
          1349.4662576687115,
          2193.6380368098157
        ]
      ],
      "shape_type": "circle"
    },
    {
      "fill_color": null,
      "flags": {},
      "id": 2,
      "label": "placa",
      "line_color": [
        18,
        13,
        105,
        255
      ],
      "points": [
        [
          1402.840490797546,
          2231.674846625767
        ],
        [
          1403.4539877300613,
          2258.6687116564417
        ]
      ],
      "shape_type": "circle"
    },
    {
      "fill_color": null,
      "flags": {},
      "id": 3,
      "label": "placa",
      "line_color": [
        127,
        184,
        31,
        255
      ],
      "points": [
        [
          1369.496021220159,
          2273.209549071618
        ],
        [
          1370.1559020044542,
          2298.218262806236
        ]
      ],
      "shape_type": "circle"
    },
    {
      "fill_color": null,
      "flags": {},
      "id": 4,
      "label": "placa",
      "line_color": [
        88,
        94,
        159,
        255
      ],
      "points": [
        [
          1357.4610244988862,
          2322.0489977728284
        ],
        [
          1358.3518930957684,
          2346.547884187082
        ]
      ],
      "shape_type": "circle"
    },
    {
      "fill_color": null,
      "flags": {},
      "id": 5,
      "label": "placa",
      "line_color": [
        98,
        135,
        14,
        255
      ],
      "points": [
        [
          1248.2889733840307,
          2336.5019011406844
        ],
        [
          1247.9087452471485,
          2360.0760456273765
        ]
      ],
      "shape_type": "circle"
    },
    {
      "fill_color": null,
      "flags": {},
      "id": 6,
      "label": "placa",
      "line_color": [
        224,
        90,
        222,
        255
      ],
      "points": [
        [
          1252.471482889734,
          2391.6349809885933
        ],
        [
          1253.9923954372625,
          2416.730038022814
        ]
      ],
      "shape_type": "circle"
    },
    {
      "fill_color": null,
      "flags": {},
      "id": 7,
      "label": "placa",
      "line_color": [
        141,
        185,
        31,
        255
      ],
      "points": [
        [
          1279.4676806083653,
          2446.768060836502
        ],
        [
          1278.707224334601,
          2469.9619771863117
        ]
      ],
      "shape_type": "circle"
    },
    {
      "fill_color": null,
      "flags": {},
      "id": 8,
      "label": "placa",
      "line_color": [
        136,
        224,
        97,
        255
      ],
      "points": [
        [
          1279.8479087452474,
          2495.4372623574145
        ],
        [
          1278.707224334601,
          2519.771863117871
        ]
      ],
      "shape_type": "circle"
    },
    {
      "fill_color": null,
      "flags": {},
      "id": 9,
      "label": "placa",
      "line_color": [
        12,
        8,
        175,
        255
      ],
      "points": [
        [
          1264.0,
          2539.259259259259
        ],
        [
          1265.4814814814813,
          2561.037037037037
        ]
      ],
      "shape_type": "circle"
    },
    {
      "fill_color": null,
      "flags": {},
      "id": 10,
      "label": "placa",
      "line_color": [
        217,
        227,
        46,
        255
      ],
      "points": [
        [
          1277.3333333333335,
          2591.259259259259
        ],
        [
          1276.8888888888887,
          2614.962962962963
        ]
      ],
      "shape_type": "circle"
    },
    {
      "fill_color": null,
      "flags": {},
      "id": 10,
      "label": "placa",
      "line_color": [
        217,
        227,
        46,
        255
      ],
      "points": [
        [
          1139.1304347826085,
          2585.869565217391
        ],
        [
          1139.3700787401576,
          2604.7244094488187
        ]
      ],
      "shape_type": "circle"
    }
  ],
  "version": "3.17.2"
}